platea/__init__.py
platea/_version.py
platea/distributions.py
platea/random_number_generators.py
platea/special_functions.py
platea/utilities.py
platea/_cpp/__init__.py
platea/_fortran/__init__.py
platea/_fortran/dist.cpython-37m-darwin.so
platea/_fortran/ran_num_gen.cpython-37m-darwin.so
platea/_fortran/spcl_fnc.cpython-37m-darwin.so
platea/_fortran/types.cpython-37m-darwin.so
tests/__init__.py
tests/test__info.py
tests/test_distributions.py
tests/test_random_number_generators.py
tests/test_special_functions.py
tests/test_utilities.py
tests/test_run_times/__init__.py
platea-0.3.dist-info/LICENSE.md
platea-0.3.dist-info/METADATA
platea-0.3.dist-info/WHEEL
platea-0.3.dist-info/top_level.txt
platea-0.3.dist-info/RECORD
