Metadata-Version: 2.1
Name: platea
Version: 0.3
Summary: A package for statistics and numeric methods.
Home-page: https://github.com/James-Montgomery/stats
Author: James Montgomery
Author-email: jamesoneillmontgomery@gmail.com
License: UNKNOWN
Platform: UNKNOWN
Classifier: Programming Language :: Python :: 3
Classifier: License :: OSI Approved :: MIT License
Classifier: Operating System :: OS Independent
Requires-Python: >=3.6
Requires-Dist: numpy (==1.18.1)
